MANIFEST.in
README.rst
VERSION
setup.py
hitchsystem/__init__.py
hitchsystem/commandline.py
hitchsystem/utils.py
hitchsystem.egg-info/PKG-INFO
hitchsystem.egg-info/SOURCES.txt
hitchsystem.egg-info/dependency_links.txt
hitchsystem.egg-info/entry_points.txt
hitchsystem.egg-info/not-zip-safe
hitchsystem.egg-info/requires.txt
hitchsystem.egg-info/top_level.txt